{
 "type": "FeatureCollection",
 "features": [
  {
   "type": "Feature",
   "properties": {
    "name": "Rome",
    "flows": {
     "1": 18,
     "2": -93,
     "3": 64,
     "4": 88,
     "5": -97,
     "6": 34,
     "7": 69,
     "8": -31,
     "9": -85
    }
   },
   "centroid": [
    12.4964,
    41.9028,
    0
   ],
   "geometry": {
    "type": "MultiPolygon",
    "coordinates": [
     [
      [
       [
        [
         12.182293,
         42.195641
        ],
        [
         12.851931,
         42.349632
        ]
       ]
      ]
     ]
    ]
   }
  },
  {
   "type": "Feature",
   "properties": {
    "name": "Milan",
    "flows": {
     "1": 57,
     "2": 86,
     "3": 73,
     "4": 60,
     "5": -1,
     "6": 10,
     "7": -76,
     "8": 99,
     "9": -77
    }
   },
   "centroid": [
    9.19,
    45.4642,
    0
   ],
   "geometry": {
    "type": "MultiPolygon",
    "coordinates": [
     [
      [
       [
        [
         9.620533,
         45.823888
        ],
        [
         9.647763,
         45.019273
        ]
       ]
      ]
     ]
    ]
   }
  },
  {
   "type": "Feature",
   "properties": {
    "name": "Naples",
    "flows": {
     "1": 40,
     "2": 94,
     "3": 40,
     "4": 1,
     "5": 57,
     "6": 94,
     "7": 8,
     "8": 54,
     "9": 67
    }
   },
   "centroid": [
    14.2681,
    40.8518,
    0
   ],
   "geometry": {
    "type": "MultiPolygon",
    "coordinates": [
     [
      [
       [
        [
         14.656207,
         40.540441
        ],
        [
         14.022042,
         40.546113
        ]
       ]
      ]
     ]
    ]
   }
  },
  {
   "type": "Feature",
   "properties": {
    "name": "Turin",
    "flows": {
     "1": 99,
     "2": -38,
     "3": -73,
     "4": -42,
     "5": 93,
     "6": -98,
     "7": 20,
     "8": -37,
     "9": -23
    }
   },
   "centroid": [
    7.6869,
    45.0703,
    0
   ],
   "geometry": {
    "type": "MultiPolygon",
    "coordinates": [
     [
      [
       [
        [
         7.390309,
         45.415663
        ],
        [
         7.209643,
         45.380383
        ]
       ]
      ]
     ]
    ]
   }
  },
  {
   "type": "Feature",
   "properties": {
    "name": "Palermo",
    "flows": {
     "1": 1,
     "2": -59,
     "3": -88,
     "4": 15,
     "5": 83,
     "6": 9,
     "7": -29,
     "8": 19,
     "9": -11
    }
   },
   "centroid": [
    13.3615,
    38.1157,
    0
   ],
   "geometry": {
    "type": "MultiPolygon",
    "coordinates": [
     [
      [
       [
        [
         13.733536,
         38.555509
        ],
        [
         13.815015,
         38.468465
        ]
       ]
      ]
     ]
    ]
   }
  },
  {
   "type": "Feature",
   "properties": {
    "name": "Genoa",
    "flows": {
     "1": -22,
     "2": -36,
     "3": -85,
     "4": 28,
     "5": -60,
     "6": 59,
     "7": -47,
     "8": -46,
     "9": 1
    }
   },
   "centroid": [
    8.9463,
    44.4056,
    0
   ],
   "geometry": {
    "type": "MultiPolygon",
    "coordinates": [
     [
      [
       [
        [
         8.54192,
         44.827614
        ],
        [
         9.368749,
         44.721339
        ]
       ]
      ]
     ]
    ]
   }
  },
  {
   "type": "Feature",
   "properties": {
    "name": "Bologna",
    "flows": {
     "1": -40,
     "2": 95,
     "3": 33,
     "4": -91,
     "5": -21,
     "6": -6,
     "7": 77,
     "8": 63,
     "9": 76
    }
   },
   "centroid": [
    11.3426,
    44.4949,
    0
   ],
   "geometry": {
    "type": "MultiPolygon",
    "coordinates": [
     [
      [
       [
        [
         11.705929,
         44.878245
        ],
        [
         10.964237,
         44.186719
        ]
       ]
      ]
     ]
    ]
   }
  },
  {
   "type": "Feature",
   "properties": {
    "name": "Florence",
    "flows": {
     "1": -1,
     "2": -32,
     "3": -11,
     "4": 59,
     "5": -100,
     "6": 56,
     "7": -22,
     "8": 24,
     "9": 33
    }
   },
   "centroid": [
    11.2558,
    43.7696,
    0
   ],
   "geometry": {
    "type": "MultiPolygon",
    "coordinates": [
     [
      [
       [
        [
         11.47441,
         44.091908
        ],
        [
         10.705654,
         43.281227
        ]
       ]
      ]
     ]
    ]
   }
  },
  {
   "type": "Feature",
   "properties": {
    "name": "Venice",
    "flows": {
     "1": 68,
     "2": 98,
     "3": 44,
     "4": 65,
     "5": 1,
     "6": -6,
     "7": -22,
     "8": -91,
     "9": -81
    }
   },
   "centroid": [
    12.3155,
    45.4408,
    0
   ],
   "geometry": {
    "type": "MultiPolygon",
    "coordinates": [
     [
      [
       [
        [
         12.634877,
         45.829149
        ],
        [
         12.613986,
         45.060636
        ]
       ]
      ]
     ]
    ]
   }
  },
  {
   "type": "Feature",
   "properties": {
    "name": "Verona",
    "flows": {
     "1": -49,
     "2": -79,
     "3": 2,
     "4": 21,
     "5": 87,
     "6": -4,
     "7": -28,
     "8": -80,
     "9": 6
    }
   },
   "centroid": [
    10.9916,
    45.4384,
    0
   ],
   "geometry": {
    "type": "MultiPolygon",
    "coordinates": [
     [
      [
       [
        [
         10.446703,
         46.002711
        ],
        [
         11.209383,
         45.873299
        ]
       ]
      ]
     ]
    ]
   }
  }
 ]
}